rjfinance/__init__.py
rjfinance/main.py
rjfinance/test.py
rjfinance-0.1.1.dist-info/LICENSE
rjfinance-0.1.1.dist-info/METADATA
rjfinance-0.1.1.dist-info/WHEEL
rjfinance-0.1.1.dist-info/top_level.txt
rjfinance-0.1.1.dist-info/RECORD
