Metadata-Version: 2.1
Name: rjfinance
Version: 0.1.1
Summary: A package for stock pattern extraction and matching using cosine similarity
Home-page: UNKNOWN
Author: Rayjada Jyotiradityasing
Author-email: rjyotiraditya@gmail.com
License: UNKNOWN
Platform: UNKNOWN
Classifier: Programming Language :: Python :: 3
Classifier: Operating System :: OS Independent
Requires-Python: >=3.7
License-File: LICENSE
Requires-Dist: pandas
Requires-Dist: scikit-learn
